{
    "products":[
        {
            "_id":"dress1",
            "title":"Dress 1",
            "image":"./images/dress1.jpg",
            "description": "Midi sundress wit shirring detail",
            "availableSizes":["X","L","XL","XXL"],
            "price": 29.99
        },
        {
            "_id":"dress2",
            "title":"Dress 2",
            "image":"./images/dress2.jpg",
            "description": "Midi sundress wit ruched detail",
            "availableSizes":["X","M","L"],
            "price": 18.99
        },
        {
            "_id":"dress3",
            "title":"Dress3",
            "image":"./images/dress3.jpg",
            "description": "Midi sundress wit shirring detail",
            "availableSizes":["X","L","XL","XXL"],
            "price": 37.99
        },
        {
            "_id":"dress4",
            "title":"Dress 4",
            "image":"./images/dress4.jpg",
            "description": "Midi sundress wit shirring detail",
            "availableSizes":["X","L","XL","XXL"],
            "price": 59.99
        },
        {
            "_id":"dress5",
            "title":"Dress 5",
            "image":"./images/dress5.jpg",
            "description": "Frill mini dress in yellow polka dot",
            "availableSizes":["X","L","XL"],
            "price": 10.99
        },
        {
            "_id":"dress6",
            "title":"Dress 6",
            "image":"./images/dress6.jpg",
            "description": "Mini tea dress in blue and red spot",
            "availableSizes":["XL","XXL"],
            "price": 49.99
        }
        
    ]
}